Workbook

Sheet Assumptions
B2: Digital Workplace Automation Priority Model
B3: Baseline assumptions driving the scoring matrix. Edit yellow cells to test scenarios
B5: Assumption | C5: Value | D5: Source / Basis
B6: Reference company size (employees) | C6: 5000 | D6: Modeled on Avatier 2026 enterprise reference calculator
B7: Loaded IT labor rate ($/hr) | C7: 45 | D7: Synthetic assumption; BLS blended IT support labor range ~$35-55/hr
B8: Password resets / year (at reference size) | C8: 18000 | D8: Avatier 2026: ~30% reset volume for 5,000 employees
B9: Password-related ticket share (of all IT tickets) | C9: 0.35 | D9: Gartner: 20-50% of help desk tickets are password-related (midpoint used)
B10: Cost per password reset (low estimate) | C10: 25 | D10: Forrester, cited in Avatier 2026 enterprise reference
B11: Cost per password reset (high estimate) | C11: 70 | D11: Forrester, cited in Matrix42, Mar 2026
B13: Implementation & Licensing Cost Assumptions (real market benchmarks)
B14: ServiceNow scoped single-workflow build (one-time) | C14: 30000 | D14: Quackback 2026: ServiceNow implementation partner fees range $30K (basic setup) to $450K+ (full enterprise). Floor used since Micron already licenses ServiceNow per JD.
B15: Password reset (SSPR) license ($/user/month) | C15: 1.5 | D15: PortalGuard Commercial On-Premises SSPR, per G2 pricing overview, 2026
B16: Password reset integration effort (one-time) | C16: 10000 | D16: Synthetic estimate for AD/ServiceNow integration labor (no exact figure published)
B17: Shift-handoff tool license ($/user/month, low tier) | C17: 5 | D17: ZipDo 2026: shift handover software starts at $5/user/month, scaling to $10+/user/month enterprise
B18: Shift-handoff rollout effort (one-time) | C18: 15000 | D18: Synthetic estimate for mobile tool rollout/config labor (no exact figure published)
B19: Meeting room booking ($/room/month) | C19: 12 | D19: Archie 2026: room-based pricing $8-20/room/month; midpoint used, recommended over per-user pricing for high-headcount/few-room orgs
B20: Meeting room booking setup (one-time) | C20: 5000 | D20: Synthetic estimate for basic rollout/config labor (no exact figure published)
B21: Risk-adjustment haircut (applied to savings) | C21: 0.2 | D21: Conservative buffer for adoption lag, partial rollout, and estimation error. Standard practice in ROI modeling, not a sourced figure
B23: Legend
B24: Yellow cells | C24: editable inputs / assumptions
B25: White cells | C25: formulas, recalculate automatically

Sheet Scoring_Matrix
A1: Automation Opportunity Prioritization Matrix
A2: Priority Score = (Feasibility x Impact) / Risk | Yellow = editable input, White = formula
A4: Workflow | B4: Category | C4: Est. Freq/Month | D4: Avg Manual Time (min) | E4: Manual Annual Hours | F4: Feasibility (1-5) | G4: Impact (1-5) | H4: Risk (1-5) | I4: Priority Score | J4: Benchmark Time Reduction % | K4: Est. Hours Saved/Year | L4: Est. Annual Cost Savings ($) | M4: Key Benchmark Stat | N4: Source | O4: Standardization (1-5) | P4: Enhanced Priority Score (F x I x S / R)
A5: New-Hire Device & Access Provisioning | B5: Office | C5: 20 | D5: 624 | E5: =C5*D5*12/60 -> 2496 | F5: 4 | G5: 5 | H5: 2 | I5: =(F5*G5)/H5 -> 10 | J5: 0.7 | K5: =E5*J5 -> 1747.2 | L5: =K5*Assumptions!$C$7 -> 78624 | M5: Manual onboarding = 10.4 hrs/hire admin time; automation cuts admin time 70% | N5: SHRM 2025 Human Capital Benchmarking Report; Customer Times 2026 Guide | O5: 4 | P5: =(F5*G5*O5)/H5 -> 40
A6: Shift-Handoff Documentation & Reporting | B6: Fab-adjacent | C6: 900 | D6: 18 | E6: =C6*D6*12/60 -> 3240 | F6: 3 | G6: 5 | H6: 3 | I6: =(F6*G6)/H6 -> 5 | J6: 0.85 | K6: =E6*J6 -> 2754 | L6: =K6*Assumptions!$C$7 -> 123930 | M6: Handover time itself: 18 min -> <30 sec via voice memo + AI summary (~97% reduction; capped at 85% here as a conservative estimate). Separate, non-time metric: digital handover tools cut production downtime 20% (Eviview): a real operational benefit, not double-counted in hours-saved calc. | N6: Teamazing, Aug 2026 (handover-time stat); Eviview, Feb 2025 (downtime stat, informational only) | O6: 2 | P6: =(F6*G6*O6)/H6 -> 10
A7: Equipment / Tool Request Approval | B7: Fab-adjacent | C7: 300 | D7: 20 | E7: =C7*D7*12/60 -> 1200 | F7: 5 | G7: 3 | H7: 1 | I7: =(F7*G7)/H7 -> 15 | J7: 0.7 | K7: =E7*J7 -> 840 | L7: =K7*Assumptions!$C$7 -> 37800 | M7: Up to 70% of asset tracking/mgmt tasks automatable. Note: source measures approval TURNAROUND (elapsed wait, days->hours), not labor time. 20 min/request is a synthetic labor-effort estimate, not sourced. | N7: Velocity Smart, Jul 2026 (turnaround stat only; labor-time estimate is synthetic) | O7: 5 | P7: =(F7*G7*O7)/H7 -> 75
A8: Password / Access Reset | B8: Office | C8: 1500 | D8: 12 | E8: =C8*D8*12/60 -> 3600 | F8: 5 | G8: 4 | H8: 2 | I8: =(F8*G8)/H8 -> 10 | J8: 0.7 | K8: =E8*J8 -> 2520 | L8: =K8*Assumptions!$C$7 -> 113400 | M8: 20-50% of help desk tickets are password-related; self-service automation cuts volume 60-90%. 12 min/reset is a synthetic estimate informed by 'several minutes per incident' language in source (no exact figure given). | N8: Gartner (via Matrix42, Mar 2026); Avatier 2026 | O8: 5 | P8: =(F8*G8*O8)/H8 -> 50
A9: Meeting / Resource Booking | B9: Office | C9: 2000 | D9: 5 | E9: =C9*D9*12/60 -> 2000 | F9: 5 | G9: 2 | H9: 1 | I9: =(F9*G9)/H9 -> 10 | J9: 0.4 | K9: =E9*J9 -> 800 | L9: =K9*Assumptions!$C$7 -> 36000 | M9: No industry benchmark found. Estimate based on comparable low-complexity self-service automation cases | N9: Synthetic estimate (no external benchmark located) | O9: 5 | P9: =(F9*G9*O9)/H9 -> 50
A11: TOTAL | K11: =SUM(K5:K9) -> 8661.2 | L11: =SUM(L5:L9) -> 389754
A13: Note: Rank by Priority Score (col I) descending to identify top automation candidates. Freq/Month, Manual Time, Feasibility, Impact, Risk, and Reduction % are editable (yellow). Adjust to test scenarios.
A14: Enhanced Priority Score (col P) adds Standardization, the criterion published RPA-candidate-selection research (process mining literature; Analytic Hierarchy Process studies with RPA practitioners) identifies as more predictive of automation success than the original 3-axis model alone. Equipment/Tool Request ranks #1 under both models, reinforcing that recommendation independently of which scoring approach is used.

Sheet Benchmark_Sources
A1: Benchmark Source Log
A2: Full citation trail for every stat used in the scoring matrix
A4: Workflow | B4: Stat | C4: Source | D4: Date / Age | E4: URL
A5: Onboarding/Provisioning | B5: 10.4 hrs of admin time per new hire (manual) | C5: SHRM 2025 Human Capital Benchmarking Report | D5: 2025 | E5: cited via ustechautomations.com
A6: Onboarding/Provisioning | B6: 70% reduction in administrative time post-automation | C6: Customer Times, 2026 Guide | D6: 2026 | E6: customertimes.com/blogs/employee-onboarding-automation
A7: Onboarding/Provisioning | B7: 54% greater new-hire productivity in first 90 days | C7: Brandon Hall Group 2025 Onboarding Benchmark Study | D7: 2025 | E7: cited via ustechautomations.com
A8: Shift-Handoff | B8: Digital handover tool cut downtime 20% | C8: Eviview | D8: Feb 18, 2025 | E8: eviview (industry case study)
A9: Shift-Handoff | B9: 18-min verbal handover, 50% detail lost in first 2 hrs; AI summary <30 sec | C9: Teamazing | D9: Aug 8, 2026 | E9: teamazing (industry case study)
A10: Shift-Handoff | B10: 80% reduction in manual documentation time; ~100 workdays saved/project in turnover delivery | C10: EIDA | D10: Nov 19, 2025 | E10: eida (industry case study)
A11: Equipment/Tool Request | B11: Up to 70% of asset tracking/mgmt tasks automatable | C11: Velocity Smart | D11: Jul 2026 | E11: velocity-smart.com/velocity-hub/blog/workflow-driven-asset-management-enterprises
A12: Equipment/Tool Request | B12: Approval turnaround shrinks from days to hours | C12: Velocity Smart | D12: Jul 15, 2026 | E12: velocity-smart.com/velocity-hub/blog/automate-asset-approval
A13: Password Reset | B13: 20-50% of help desk tickets are password-related | C13: Gartner, cited in Matrix42 | D13: Mar 18, 2026 | E13: matrix42 (Gartner citation)
A14: Password Reset | B14: $25 avg cost per reset (labor+infra+productivity) | C14: Forrester, cited in Avatier | D14: 2026 | E14: credentialgovernance.avatier.com
A15: Password Reset | B15: $70 avg cost per reset | C15: Forrester, cited in Matrix42 | D15: Mar 18, 2026 | E15: matrix42
... A28: External Validation (non-Micron) | B28: IT service desk automation and ITSM integration case study, workflow automation and bot use to address manual workload | C28: AG Barr ITSM case study | D28: 2026 | E28: aimultiple.com/itsm-case-studies

Sheet ROI_Model
A1: 3-Year ROI Model
A2: Annual Savings linked from Scoring_Matrix. Cost basis: real market benchmarks (Assumptions tab) where available, synthetic labor estimates flagged.
A4: Workflow | B4: Annual Savings (linked) | C4: Implementation Basis | D4: One-Time Cost | E4: Annual License Cost | F4: Year 1 Net | G4: Year 2 Net | H4: Year 3 Net | I4: 3-Yr Cumulative Net | J4: Payback (months) | K4: Risk-Adj. Savings (-20%) | L4: Risk-Adj. 3-Yr Net | M4: Risk-Adj. Payback (months)
A5: New-Hire Device & Access Provisioning | B5: =Scoring_Matrix!L5 -> 78624 | C5: Build within existing ServiceNow instance (Micron already licenses ServiceNow per JD) | D5: 30000 | E5: 0 | F5: =B5-D5-E5 -> 48624 | G5: =B5-E5 -> 78624 | H5: =B5-E5 -> 78624 | I5: =F5+G5+H5 -> 205872 | J5: =IF((B5-E5)>0,D5/((B5-E5)/12),"N/A") -> 4.5787546 | K5: =B5*(1-Assumptions!$C$21) -> 62899.2 | L5: =(K5-E5)*3-D5 -> 158697.6 | M5: =IF((K5-E5)>0,D5/((K5-E5)/12),"N/A") -> 5.7234432
A6: Shift-Handoff Documentation & Reporting | B6: =Scoring_Matrix!L6 -> 123930 | C6: Dedicated mobile shift-handover tool (not native to ServiceNow) + rollout labor | D6: 15000 | E6: =1000*Assumptions!$C$17*12 -> 60000 | F6: =B6-D6-E6 -> 48930 | G6: =B6-E6 -> 63930 | H6: =B6-E6 -> 63930 | I6: =F6+G6+H6 -> 176790 | J6: =IF((B6-E6)>0,D6/((B6-E6)/12),"N/A") -> 2.8155795 | K6: =B6*(1-Assumptions!$C$21) -> 99144 | L6: =(K6-E6)*3-D6 -> 102432 | M6: =IF((K6-E6)>0,D6/((K6-E6)/12),"N/A") -> 4.5984059
A7: Equipment / Tool Request Approval | B7: =Scoring_Matrix!L7 -> 37800 | C7: Build within existing ServiceNow instance (shares platform with onboarding build) | D7: 30000 | E7: 0 | F7: =B7-D7-E7 -> 7800 | G7: =B7-E7 -> 37800 | H7: =B7-E7 -> 37800 | I7: =F7+G7+H7 -> 83400 | J7: =IF((B7-E7)>0,D7/((B7-E7)/12),"N/A") -> 9.5238095 | K7: =B7*(1-Assumptions!$C$21) -> 30240 | L7: =(K7-E7)*3-D7 -> 60720 | M7: =IF((K7-E7)>0,D7/((K7-E7)/12),"N/A") -> 11.904762
A8: Password / Access Reset | B8: =Scoring_Matrix!L8 -> 113400 | C8: Dedicated SSPR tool licensed per employee + integration labor | D8: 10000 | E8: =Assumptions!$C$6*Assumptions!$C$15*12 -> 90000 | F8: =B8-D8-E8 -> 13400 | G8: =B8-E8 -> 23400 | H8: =B8-E8 -> 23400 | I8: =F8+G8+H8 -> 60200 | J8: =IF((B8-E8)>0,D8/((B8-E8)/12),"N/A") -> 5.1282051 | K8: =B8*(1-Assumptions!$C$21) -> 90720 | L8: =(K8-E8)*3-D8 -> -7840 | M8: =IF((K8-E8)>0,D8/((K8-E8)/12),"N/A") -> 166.66667
A9: Meeting / Resource Booking | B9: =Scoring_Matrix!L9 -> 36000 | C9: Dedicated room-booking tool, priced per room (cheaper than per-user at this headcount) | D9: 5000 | E9: =50*Assumptions!$C$19*12 -> 7200 | F9: =B9-D9-E9 -> 23800 | G9: =B9-E9 -> 28800 | H9: =B9-E9 -> 28800 | I9: =F9+G9+H9 -> 81400 | J9: =IF((B9-E9)>0,D9/((B9-E9)/12),"N/A") -> 2.0833333 | K9: =B9*(1-Assumptions!$C$21) -> 28800 | L9: =(K9-E9)*3-D9 -> 59800 | M9: =IF((K9-E9)>0,D9/((K9-E9)/12),"N/A") -> 2.7777778
A11: TOTAL | I11: =SUM(I5:I9) -> 607662 | L11: =SUM(L5:L9) -> 373809.6
A13: Note: Onboarding and Equipment builds assume reuse of Micron's existing ServiceNow instance (per JD tool list), no separate licensing. Password Reset, Shift-Handoff, and Meeting Booking assume new dedicated tools with real published per-user/per-room pricing (see Assumptions tab). Shift-worker and room counts are synthetic subset estimates, flagged accordingly.
A15: Bundled Implementation Scenario (Onboarding + Equipment, same ServiceNow build)
A16: Both builds are costed separately above ($30,000 each) as a conservative baseline. In practice, they share the same platform, admin team, and sprint (see Sprint_Backlog, Sprint 1), so combining them plausibly costs less than two independent builds.
A18: Scenario | B18: Onboarding One-Time | C18: Equipment One-Time | D18: Combined One-Time | E18: 3-Yr Combined Savings | F18: Combined 3-Yr Net
A19: Baseline (separate builds) | B19: =D5 -> 30000 | C19: =D7 -> 30000 | D19: =B19+C19 -> 60000 | E19: =(B5*3)+(B7*3) -> 349272 | F19: =E19-D19 -> 289272
A20: Bundled (25% synergy discount, editable) | B20: n/a (shared build) | C20: n/a (shared build) | D20: =D19*(1-0.25) -> 45000 | E20: =E19 -> 349272 | F20: =E20-D20 -> 304272
A22: 25% is an editable planning assumption, not a sourced figure: it estimates shared discovery, ServiceNow admin setup, and testing effort. Adjust column D's formula input if your organization's actual shared-build savings differ.

Sheet Sensitivity_Analysis
A1: Sensitivity Analysis: How Fragile Is Each Ranking?
A2: Priority Score depends on subjective 1-5 ratings. This shows how much the score moves if any single rating is off by 1 point.
A4: Workflow | B4: Baseline F | C4: Baseline I | D4: Baseline R | E4: Baseline Score | F4: Score if F-1 | G4: Score if F+1 | H4: Score if I-1 | I4: Score if I+1 | J4: Score if R-1 | K4: Score if R+1 | L4: Score Range | M4: Most Sensitive To
A5: New-Hire Device & Access Provisioning | B5: 4 | C5: 5 | D5: 2 | E5: =(B5*C5)/D5 -> 10 | F5: =(MAX(1,B5-1)*C5)/D5 -> 7.5 | G5: =(MIN(5,B5+1)*C5)/D5 -> 12.5 | H5: =(B5*MAX(1,C5-1))/D5 -> 8 | I5: =(B5*MIN(5,C5+1))/D5 -> 10 | J5: =(B5*C5)/MAX(1,D5-1) -> 20 | K5: =(B5*C5)/MIN(5,D5+1) -> 6.6666667 | L5: =MAX(F5:K5)-MIN(F5:K5) -> 13.333333 | M5: =IF(ABS(F5-G5)>=ABS(H5-I5),IF(ABS(F5-G5)>=ABS(J5-K5),"Feasibility","Risk"),IF(ABS(H5-I5)>=ABS(J5-K5),"Impact","Risk")) -> Risk
A6: Shift-Handoff Documentation & Reporting | B6: 3 | C6: 5 | D6: 3 | E6: =(B6*C6)/D6 -> 5 | F6: =(MAX(1,B6-1)*C6)/D6 -> 3.3333333 | G6: =(MIN(5,B6+1)*C6)/D6 -> 6.6666667 | H6: =(B6*MAX(1,C6-1))/D6 -> 4 | I6: =(B6*MIN(5,C6+1))/D6 -> 5 | J6: =(B6*C6)/MAX(1,D6-1) -> 7.5 | K6: =(B6*C6)/MIN(5,D6+1) -> 3.75 | L6: =MAX(F6:K6)-MIN(F6:K6) -> 4.1666667 | M6: =IF(ABS(F6-G6)>=ABS(H6-I6),IF(ABS(F6-G6)>=ABS(J6-K6),"Feasibility","Risk"),IF(ABS(H6-I6)>=ABS(J6-K6),"Impact","Risk")) -> Risk
A7: Equipment / Tool Request Approval | B7: 5 | C7: 3 | D7: 1 | E7: =(B7*C7)/D7 -> 15 | F7: =(MAX(1,B7-1)*C7)/D7 -> 12 | G7: =(MIN(5,B7+1)*C7)/D7 -> 15 | H7: =(B7*MAX(1,C7-1))/D7 -> 10 | I7: =(B7*MIN(5,C7+1))/D7 -> 20 | J7: =(B7*C7)/MAX(1,D7-1) -> 15 | K7: =(B7*C7)/MIN(5,D7+1) -> 7.5 | L7: =MAX(F7:K7)-MIN(F7:K7) -> 12.5 | M7: =IF(ABS(F7-G7)>=ABS(H7-I7),IF(ABS(F7-G7)>=ABS(J7-K7),"Feasibility","Risk"),IF(ABS(H7-I7)>=ABS(J7-K7),"Impact","Risk")) -> Impact
A8: Password / Access Reset | B8: 5 | C8: 4 | D8: 2 | E8: =(B8*C8)/D8 -> 10 | F8: =(MAX(1,B8-1)*C8)/D8 -> 8 | G8: =(MIN(5,B8+1)*C8)/D8 -> 10 | H8: =(B8*MAX(1,C8-1))/D8 -> 7.5 | I8: =(B8*MIN(5,C8+1))/D8 -> 12.5 | J8: =(B8*C8)/MAX(1,D8-1) -> 20 | K8: =(B8*C8)/MIN(5,D8+1) -> 6.6666667 | L8: =MAX(F8:K8)-MIN(F8:K8) -> 13.333333 | M8: =IF(ABS(F8-G8)>=ABS(H8-I8),IF(ABS(F8-G8)>=ABS(J8-K8),"Feasibility","Risk"),IF(ABS(H8-I8)>=ABS(J8-K8),"Impact","Risk")) -> Risk
A9: Meeting / Resource Booking | B9: 5 | C9: 2 | D9: 1 | E9: =(B9*C9)/D9 -> 10 | F9: =(MAX(1,B9-1)*C9)/D9 -> 8 | G9: =(MIN(5,B9+1)*C9)/D9 -> 10 | H9: =(B9*MAX(1,C9-1))/D9 -> 5 | I9: =(B9*MIN(5,C9+1))/D9 -> 15 | J9: =(B9*C9)/MAX(1,D9-1) -> 10 | K9: =(B9*C9)/MIN(5,D9+1) -> 5 | L9: =MAX(F9:K9)-MIN(F9:K9) -> 10 | M9: =IF(ABS(F9-G9)>=ABS(H9-I9),IF(ABS(F9-G9)>=ABS(J9-K9),"Feasibility","Risk"),IF(ABS(H9-I9)>=ABS(J9-K9),"Impact","Risk")) -> Impact
A11: Reading this table: a workflow whose score swings widely under a 1-point rating change is a fragile ranking, one where reasonable people scoring it slightly differently would reach a different conclusion. Equipment/Tool Request's top score is most sensitive to its Impact rating, not Feasibility or Risk: if Impact were scored a 4 instead of a 3, its priority score would jump from 15 to 20.
A13: Chart data (Equipment/Tool Request perturbation range)
A14: Axis | B14: Low | C14: High
A15: Feasibility | B15: =F7 -> 12 | C15: =G7 -> 15
A16: Impact | B16: =H7 -> 10 | C16: =I7 -> 20
A17: Risk | B17: =J7 -> 15 | C17: =K7 -> 7.5
